pyplaywrightwsrecorder/__init__.py
pyplaywrightwsrecorder/recorder.py
pyplaywrightwsrecorder-0.0.2.dist-info/LICENSE
pyplaywrightwsrecorder-0.0.2.dist-info/METADATA
pyplaywrightwsrecorder-0.0.2.dist-info/WHEEL
pyplaywrightwsrecorder-0.0.2.dist-info/top_level.txt
pyplaywrightwsrecorder-0.0.2.dist-info/RECORD
