Metadata-Version: 2.1
Name: pyplaywrightwsrecorder
Version: 0.0.2
Summary: Python Playwright Websocket recorder.
Author: Satyam Sinha
License-File: LICENSE
